MANIFEST.in
README.md
dev_requirements.txt
requirements.txt
setup.py
fast5_research/__init__.py
fast5_research/extract.py
fast5_research/fast5.py
fast5_research/fast5_bulk.py
fast5_research/util.py
fast5_research.egg-info/PKG-INFO
fast5_research.egg-info/SOURCES.txt
fast5_research.egg-info/dependency_links.txt
fast5_research.egg-info/entry_points.txt
fast5_research.egg-info/requires.txt
fast5_research.egg-info/top_level.txt
fast5_research.egg-info/zip-safe