Metadata-Version: 2.1
Name: fast5-research
Version: 1.2.18
Summary: ONT Research .fast5 read/write API.
Home-page: https://github.com/nanoporetech/fast5_research
Author: cwright
Author-email: cwright@nanoporetech.com
License: Mozilla Public License 2.0
Keywords: ONT Research fast5 API
Platform: UNKNOWN
Classifier: Development Status :: 4 - Beta
Classifier: Intended Audience :: Science/Research
Classifier: License :: OSI Approved :: Mozilla Public License 2.0 (MPL 2.0)
Classifier: Natural Language :: English
Classifier: Programming Language :: Python
Classifier: Topic :: Software Development :: Libraries :: Python Modules
Classifier: Topic :: Scientific/Engineering :: Bio-Informatics
